[
    {
        "projectUrl": "https://discord.gg/storm",
        "provider": "Storm 2",
        "name": "Altarts AIO RC",
        "description": "Altarts AIO RC Altar",
        "id": "altartsaiorc-plugin",
        "releases": [
            {
                "date": "2025-02-12",
                "sha512sum": "2ECC46ABD48A7E9AE576A0D7269A38559220D016849F051741685873684A515974AF0C63B033A0E6DA2F684ED515438A62DC52A4DBE3A529880202950514D791",
                "version": "0.0.2",
                "url": "https://raw.githubusercontent.com/lau-nielsen/alt-art-plugins/main/aio-rc-altar-0.0.2.jar",
                "requires": "^1.0.0"
            },
            {
                "date": "2025-02-13",
                "sha512sum": "91D14B90178621D91037C8FBD1CFC7FAD108DCDA2581B2B4B685C82C3FEB6EFE3FA41CF21CC754E6EA589A5564C565FD3E0EC1E963D755684EA12624547195EB",
                "version": "0.0.5",
                "url": "https://raw.githubusercontent.com/lau-nielsen/alt-art-plugins/main/aio-rc-altar-0.0.5.jar",
                "requires": "^1.0.0"
            }
        ]
    },
    {
        "projectUrl": "https://discord.gg/storm",
        "provider": "Storm 2",
        "name": "Altarts Cure Me",
        "description": "Altarts Cure Me",
        "id": "altartscureme-plugin",
        "releases": [
            {
                "date": "2025-02-10",
                "sha512sum": "0A3861B85232516FDD80F565D9AC05EF5F7A032F7EF1ADDA63F2228F0B960D4233F0B494A8DB4532265A6AB2B5C8464C86CE384DBE3C293FD776922A21C2FF0F",
                "version": "0.0.1",
                "url": "https://raw.githubusercontent.com/lau-nielsen/alt-art-plugins/main/cure-me-0.0.1.jar",
                "requires": "^1.0.0"
            },
            {
                "date": "2025-02-12",
                "sha512sum": "8614C2BF9600AE8F20962CFB53D9500D0738B959440F353679622048797341A769D45697A557D987681606E1B59EE6B807496778B11E8398B6CBF14CFFEACBC6",
                "version": "0.0.3",
                "url": "https://raw.githubusercontent.com/lau-nielsen/alt-art-plugins/main/cure-me-0.0.3.jar",
                "requires": "^1.0.0"
            },
            {
                "date": "2025-02-13",
                "sha512sum": "CE20C8C8D75205F241B8311FED0E203558B371CF9D1DE5C36CBD7AE257822297BC7619CAB15C213A16EBE97AB18726A0EC0F30C08D0F2776848FD96B23D0D148",
                "version": "0.0.4",
                "url": "https://raw.githubusercontent.com/lau-nielsen/alt-art-plugins/main/cure-me-0.0.4.jar",
                "requires": "^1.0.0"
            }
        ]
    },
    {
        "projectUrl": "https://discord.gg/storm",
        "provider": "Storm 2",
        "name": "Altarts Daeyalt miner",
        "description": "Altarts Daeyalt miner",
        "id": "altartsdaeyaltminer-plugin",
        "releases": [
            {
                "date": "2025-02-13",
                "sha512sum": "C61D0B68F43FC619F7F568153B7C95164FA0B6048973ED29CD15B32BD90335B7651AF4C5EA36C1540A3CBCDD02BF2878C43EB0CED7EF1A6D7499BB21409DDA99",
                "version": "0.0.4",
                "url": "https://raw.githubusercontent.com/lau-nielsen/alt-art-plugins/main/daeyalt-miner-0.0.4.jar",
                "requires": "^1.0.0"
            }
        ]
    },
    {
        "projectUrl": "https://discord.gg/storm",
        "provider": "Storm 2",
        "name": "Altarts Glory Recharger",
        "description": "Altarts Glory Recharger",
        "id": "altartsgloryrecharger-plugin",
        "releases": [
            {
                "date": "2025-02-10",
                "sha512sum": "3876AC4A2E11D793EEED3D09BAA5444B61C0252C406A7DA82B6AA3C54B0F241A676E37273F21C354A498413F9B00B449A006A20AAE53958AE8673A1A43E25F0B",
                "version": "0.0.2",
                "url": "https://raw.githubusercontent.com/lau-nielsen/alt-art-plugins/main/glory-recharger-0.0.2.jar",
                "requires": "^1.0.0"
            },
            {
                "date": "2025-02-13",
                "sha512sum": "6D954CC937C5BC545F71EFFB8C85C287F960292B9AC598FE1A6A8FEB15401406039CB99CEE20113FB08B1471BA7F3A3258AB065C7856546C621324D2EAA62438",
                "version": "0.0.4",
                "url": "https://raw.githubusercontent.com/lau-nielsen/alt-art-plugins/main/glory-recharger-0.0.4.jar",
                "requires": "^1.0.0"
            }
        ]
    },
    {
        "projectUrl": "https://discord.gg/storm",
        "provider": "Storm 2",
        "name": "Altarts Kourend RC",
        "description": "Altarts Kourend RC",
        "id": "altartskourendrc-plugin",
        "releases": [
            {
                "date": "2025-02-13",
                "sha512sum": "DE9B328A8C72CAD898BD97902761022523302283D66F1A74039FA98698B506156289AE97536E98278D36EEE8A1FB1772ED0D673BF4AE6D3D87F9FE14DB754DEC",
                "version": "0.0.2",
                "url": "https://raw.githubusercontent.com/lau-nielsen/alt-art-plugins/main/kourend-rc-0.0.2.jar",
                "requires": "^1.0.0"
            }
        ]
    },
    {
        "projectUrl": "https://discord.gg/storm",
        "provider": "Storm 2",
        "name": "Altarts Planker",
        "description": "Altarts Planker",
        "id": "altartsplanker-plugin",
        "releases": [
            {
                "date": "2025-02-13",
                "sha512sum": "A653F43CD761755F296BAA31FAB13E04F8CD758B84BB86914A15108E38D59A41B34FFF9D9CB9CD35B8C606F2C87D6489541A665A9460EAE47C916133DBF97018",
                "version": "0.0.6",
                "url": "https://raw.githubusercontent.com/lau-nielsen/alt-art-plugins/main/planker-0.0.6.jar",
                "requires": "^1.0.0"
            }
        ]
    },
    {
        "projectUrl": "https://discord.gg/storm",
        "provider": "Storm 2",
        "name": "Altarts Volcanic Mine",
        "description": "Altarts Volcanic Mine",
        "id": "altartsvolcanicmine-plugin",
        "releases": [
            {
                "date": "2025-02-12",
                "sha512sum": "358E9DC0CBD627D92648177D8A2D9731B8AA74D95415E564C444DA79AFBD08C0E6959E8CC80A370FD562B0D84193C8A62FA0996C1027306537C252D21F9BBE4D",
                "version": "0.0.1",
                "url": "https://raw.githubusercontent.com/lau-nielsen/alt-art-plugins/main/volcanic-mine-0.0.1.jar",
                "requires": "^1.0.0"
            },
            {
                "date": "2025-02-13",
                "sha512sum": "09396261F1C83FF8EC3F5C16BAAA0F941C8C8DCD86E28DED0690902F3B33260D28799F327B6900CF20EC0FC1F28FBBD799298D6CF4C6F88C6BAE7631EEB0E685",
                "version": "0.0.5",
                "url": "https://raw.githubusercontent.com/lau-nielsen/alt-art-plugins/main/volcanic-mine-0.0.5.jar",
                "requires": "^1.0.0"
            },
            {
                "date": "2025-02-13",
                "sha512sum": "45A88B14465B2C3B85F3C030FC9A164C9E7634AC3D7E7750B28275147702DCEA51A83CE6B9F182B0A20E5773EE06B0C262C22D82035B6A0E3F469FA95B51FED3",
                "version": "0.0.6",
                "url": "https://raw.githubusercontent.com/lau-nielsen/alt-art-plugins/main/volcanic-mine-0.0.6.jar",
                "requires": "^1.0.0"
            },
            {
                "date": "2025-02-13",
                "sha512sum": "D6598C33EC50045926E82DA128E66AC5A200D74AFB5529355E64F0D951F386E6C0F2CC69EA746A0FC35CFAF916B9F556C6D0F144848D8B66094385F66440DCA7",
                "version": "0.0.7",
                "url": "https://raw.githubusercontent.com/lau-nielsen/alt-art-plugins/main/volcanic-mine-0.0.7.jar",
                "requires": "^1.0.0"
            }
        ]
    },
    {
        "projectUrl": "https://discord.gg/storm",
        "provider": "Storm 2",
        "name": "Altarts Fungus",
        "description": "Altarts Fungus",
        "id": "altartsfungus-plugin",
        "releases": [
            {
                "date": "2025-02-13",
                "sha512sum": "E43F48B66B636B02BB9D428BC830B2732E22F821C47D8A1DD25B11104B4C2CCB32B2955D07DBC23EB240C931DBC35E73880C7541BD6243C47CD1023EC46E40E8",
                "version": "0.0.1",
                "url": "https://raw.githubusercontent.com/lau-nielsen/alt-art-plugins/main/fungus-0.0.1.jar",
                "requires": "^1.0.0"
            }
        ]
    }
]
